lamin_cli/__init__.py
lamin_cli/__main__.py
lamin_cli/_annotate.py
lamin_cli/_cache.py
lamin_cli/_context.py
lamin_cli/_delete.py
lamin_cli/_io.py
lamin_cli/_load.py
lamin_cli/_migration.py
lamin_cli/_save.py
lamin_cli/_settings.py
lamin_cli/urls.py
lamin_cli/clone/__init__.py
lamin_cli/clone/_clone_verification.py
lamin_cli/clone/create_sqlite_clone_and_import_db.py
lamin_cli/compute/__init__.py
lamin_cli/compute/modal.py
lamin_cli-1.12.0.dist-info/entry_points.txt
lamin_cli-1.12.0.dist-info/LICENSE
lamin_cli-1.12.0.dist-info/WHEEL
lamin_cli-1.12.0.dist-info/METADATA
lamin_cli-1.12.0.dist-info/RECORD
