Metadata-Version: 2.3
Name: lamin_cli
Version: 1.12.0
Summary: Lamin CLI.
Author-email: Lamin Labs <open-source@lamin.ai>
Requires-Dist: rich-click>=1.7
Project-URL: Home, https://github.com/laminlabs/lamin-cli
